README.rst
setup.py
ava/__init__.py
ava/key.py
ava_key.egg-info/PKG-INFO
ava_key.egg-info/SOURCES.txt
ava_key.egg-info/dependency_links.txt
ava_key.egg-info/entry_points.txt
ava_key.egg-info/requires.txt
ava_key.egg-info/top_level.txt
ava_key.egg-info/zip-safe