Metadata-Version: 1.1
Name: ava-key
Version: 0.2.0
Summary: Key generator and validator.
Home-page: UNKNOWN
Author: Sam Kuo
Author-email: sam@eavatar.com
License: BSD
Platform: UNKNOWN
Classifier: Development Status :: 3 - Alpha
Classifier: Topic :: Utilities
Classifier: License :: OSI Approved :: BSD License
Classifier: Programming Language :: Python
Classifier: Programming Language :: Python :: 2
Classifier: Programming Language :: Python :: 2.7
Classifier: Programming Language :: Python :: Implementation :: CPython
Classifier: Operating System :: OS Independent
